amolkit/EleInfo.py
amolkit/__init__.py
amolkit/amolsystem.py
amolkit/atom.py
amolkit/genic.py
amolkit/getEleInfo.py
amolkit/gethybridstate.py
amolkit/getring.py
amolkit/misc.py
amolkit/molecule.py
amolkit/molecule2.py
amolkit/moltransform.py
amolkit/parameter.py
amolkit/psf.py
amolkit/stringmanip.py
amolkit/topology.py
amolkit-1.0.14.dist-info/LICENSE
amolkit-1.0.14.dist-info/METADATA
amolkit-1.0.14.dist-info/WHEEL
amolkit-1.0.14.dist-info/top_level.txt
amolkit-1.0.14.dist-info/RECORD
