Metadata-Version: 2.1
Name: amolkit
Version: 1.0.14
Summary: Library for extracting molecule information
Home-page: https://github.com/anmolecule/amolkit
Author: Anmol Kumar
Author-email: anmolecule@gmail.com
License: BSD 3-Clause "New" or "Revised" License
License-File: LICENSE
